{"fleuU+o3SgezcwMZ2Dkmww==":"abstract-geometric-faceted-background-animation-4yecjn3zl-f0000-1920x1080.png","F6mbHy1MIjs4h2htIJFGpw==":"20626296_10212576867390307_3346233722882851614_o-1079x1079.jpg","G7ppxFmBiA01WEKusq5Vzg==":"01.jpg","QzC3RJ6Dy6K5hs3tKSXCQw==":"background3.jpg","dMy4NKj93Lr7JEAUASA17Q==":"background4.jpg","+tUkL3jOFYBsst/geQROpA==":"20626296_10212576867390307_3346233722882851614_o-1-1079x1079.jpg","EHLXJz30A6msu4l2DcV76A==":"background2.jpg","FbGECDu7JHS5PlYQ868w7g==":"mhand%20h1-b%20-%20concept%20b04%20(%20b%20type%20antenna%20)-3508x2480.jpg","Ifl8vz7BEFu0a/oU46yeHA==":"mhand%20h1-b%20-%20concept%20b04%20(%20b%20type%20antenna%20)-3508x2480.jpg","nAyEqFEwcWfZu4VHW5A13g==":"mhand%20h1-b%20-%20concept%20b04%20(%20b%20type%20antenna%20)-3508x2480.jpg","HpGpuhxgWz8AdjLf5uj/KQ==":"mhand%20h1-b%20-%20concept%20b%20(%20b%20type%20antenna%20)%20(no%20background)-1754x1240.jpg","0udDDF4xuFkRvcY6/dRt/Q==":"download-328x201.png","jpfuXINXog/ez7O7xXyqsg==":"flexiwhisk-3-400x300.jpg","tT2ucX9D2vjD0dTxJFKFeA==":"tongner-400x300.jpg","X3MH5aHeQPdxy2rO9oM84A==":"scolander-1-400x300.jpg","m4zo0Rqt3oQ+Z1UcYUDG0g==":"megatray-833x625.jpg","tSCBrRSnSOnAeBcGkuPZ5Q==":"mhand-833x625.jpg","SMEc/B0TC1rZhCzpRZQZbw==":"baby%20monitor-427x312.jpg","QZxVB5MIwnolVqkRRgd48g==":"baby%20monitor-400x300.jpg","8AchaSkfecXopKpLm8lNyA==":"spreader%20bar-833x625.jpg","bBAMKL20/cD+9d+RMXCrNA==":"spreader%20bar-833x625.jpg","7viNTOrz+HCkW+Oe0kKBqQ==":"audio-833x625.jpg","s1paTMgZuHSiKpVYBhE3Gw==":"beautycare-1-833x625.jpg","yen/c/a7qMxDYvyvf8B3GQ==":"flexiwhisk%201-1200x900.jpg","+FfkoTdPO7iweZqIIN6cjg==":"flexiwhisk%201-1200x900.jpg","XxqGSsOvP1F7z5teIZk0sg==":"flexiwhisk%201-1200x900.jpg","i5Q3eWybKU6ytCSbo2MDDQ==":"flexiwhisk%202-1200x900.jpg","a67q8Y5StVvpbHLs2m3oNg==":"flexiwhisk%203-1200x900.jpg","IxzyRtWkusMCq4iJOSqVTg==":"flexiwhisk%204-1200x900.jpg","YvpIuF90Ommk8Pir8b/Trg==":"tongner%201-1200x900.jpg","ALTDgGv/F7HgbVNGAOQULw==":"tongner%202-1200x900.jpg","96YPGO5LXCGRgn9aTn02IA==":"tongner%203-1200x900.jpg","93XHNWB8IKxoHS1SQIfX/g==":"tongner%204-1200x900.jpg","yWKg/kLdMDvRWYHAWcy3jg==":"scolander%201-1200x900.jpg","Csa0TNO3WKQN9nGkIWEb+A==":"scolander%202-1200x900.jpg","CmQwiRi5RxzgaZ2neKqYnQ==":"scolander%201-1200x900.jpg","mh2OBVSu6ZLDlclL5U3Tsg==":"mhand%201-1200x900.jpg","ih2MxyMO4YqfLECXqqxPQQ==":"mhand%202-1200x900.jpg","N3R1w5nNGz98a+uug1ZM4w==":"mhand%203-1200x900.jpg","EOeXw4OjMcTjZXX0V3DFIg==":"mhand%204-1200x900.jpg","WfCSt43Xlk5tOfYZ8ywfYw==":"megatray%201-1200x900.jpg","1I+4g0qu3PlCQCQ4R4t5uQ==":"megatray%201-1200x900.jpg","yUA/3Zi1X2HptvBYzQE3xQ==":"megatray%202-1200x900.jpg","fY+rmLe1+WS8c8g83vICuQ==":"baby%20monitor%201-1200x900.jpg","odekUspDuLKTwcOypfWvHA==":"baby%20monitor%201-1200x900.jpg","v02i0j0J2B0wzNYY7+dLrQ==":"baby%20monitor%201-1200x900.jpg","aDnUSQpymESIWUQHZPmC3A==":"baby%20monitor%202-1200x900.jpg","JgQQj6WQHbsoITQLTE9MFA==":"baby%20monitor%203-1200x900.jpg","US4AnDcHmBW+yCwdIN03TQ==":"baby%20monitor%204-1200x900.jpg","tu7RvBKucPHZWuE8wJEnsQ==":"baby-monitor-5-1200x900-800x600.jpg","McaLM5H4SXDC2AvmWS0zJQ==":"h102-1200x900.jpg","RuqC820fyJE2jzBmwJNfyQ==":"h102-5-1200x900.jpg","VcJkTRB2hbef7FMKUTvplQ==":"h102%203-1200x900.jpg","VCaE6XdabimrHI9NTMziFA==":"h102%204-1200x900.jpg","NTqMRAaOI5zSiOFiuNmumw==":"spreader%20bar%201-1200x900.jpg","AMB67/U0QU0mnfL0jvnAYA==":"spreader%20bar%204-1200x900.jpg","tr2vfibp/LygJXKo29BfNQ==":"spreader%20bar%202-1200x900.jpg","x+CS3ihVqERAyiIqZaIHuA==":"spreader%20bar%203-1200x900.jpg","RfDPluMx1YXk0NFNLKNMCg==":"spreader%20bar%205-1200x900.jpg","/icqGbjc8FpUmaWKUTGJRg==":"av%201-1200x900.jpg","tOjAr66ArGGL9nRGSM21Zw==":"av%202-1200x900.jpg","E4BPALSUlUioitZ5dK+GCA==":"av%203-1200x900.jpg","jsZr3VxR6lZUibwEDVQRxw==":"av%204-1200x900.jpg","zz9tvOizH4fbqqkBQSFgRg==":"av%205-1200x900.jpg","rDBDIencmsrHxltG8rovaQ==":"av%206-1200x900.jpg","oQfhdxTHBYfVyzD21gRnMw==":"av7-1200x900.jpg","CvNqPf8qExEg+XTwotRYHQ==":"av%208-1200x900.jpg","rcmMkWTG1Ick6OsZKY+C2w==":"av%209-1200x900.jpg","CAbD8U7yVqaSio6RDxRS/g==":"av%2010-1200x900.jpg","lzz/5q0UBAlaeQH5s+oIoQ==":"av%2011-1200x900.jpg","71j5GP3W+VT9o+lpmnDM5g==":"av%2012-1200x900.jpg","0YpRwNF5GY3EDic3c4eGOA==":"%E6%8E%83%E6%8F%8F0002-2000x1453.jpg","1GMo4EsXAUQnvXSRIbyxhQ==":"%E6%8E%83%E6%8F%8F0001-2000x1469.jpg","25UVg5wGL9fq2xE0bEGi/A==":"sport%201-1200x900.jpg","6RmG7BkA7DmBbkGKgFDTpg==":"beauty%20care%201-1200x900.jpg","+ech6T3pgCgRgDTElq3qgg==":"beauty%20care%201-1200x900.jpg","MPruPAPlUlOzRvPf0NFAFw==":"beauty%20care%202-1200x900.jpg","fSJch36X4wq00D4zrmzWmw==":"beauty%20care%203-1200x900.jpg","pVeh0Brds/Ulr09TcdECSw==":"beauty%20care%204-1200x900.jpg","MGfBTQMPhPnfieNU0WRhHQ==":"beauty%20care%205-1200x900.jpg","IP75sVyIGUfx1HE//V8pgw==":"beauty%20care%206-1200x900.jpg","y5cgtTFLZbszpJPLE9x/Lw==":"k%20logo-234x234.png","EnoCCA2/bG2+7S3zt6uOEA==":"k%20logo%20b-232x233.png","LbudqKT9AZQ7W3lp1BNUUw==":"k%20logo%20b%20no%20background-201x201.png","QqiB3eNEHYACVWf+UT2v9w==":"k%20logo%20b%20no%20background%202-201x201.png","lPre5bgHrUI4H2tCQm6Uwg==":"k%20logo%20b%20no%20background%203-300x300.png","jvReZVIoV00A01AfAerI0A==":"k%20logo%20b%20no%20background%203-1-300x300.png","uqvhU+PuCvjeBUrY7bMq7Q==":"23668765_10213324425838801_5535581080860648539_o-1080x1080.jpg","AEczIbtH52hjOSo04IdHrQ==":"23668765_10213324425838801_5535581080860648539_o-1-1080x1080.jpg","lbt8wOSdD3pnLYFqTFWcsw==":"20643338_10212576787868319_3674512243604160434_o-1079x1079.jpg","pgGXdHgW1+l4HWHQnY6Sbg==":"dsc01293-1920x1080.jpg","wEffbWFITZapR58/2kybOA==":"22135775_10213010641194381_5071429523400634994_o-1080x1080.jpg","Kyq65ZI+rcN8EG2yewRfrA==":"22135775_10213010641194381_5071429523400634994_o-1-1080x1080.jpg","XFWaw4kF2dlGWzWdAELLlQ==":"23668765_10213324425838801_5535581080860648539_o-2-1080x1080.jpg","Szl154p4MUBTonTd04euKg==":"305528_4525503049303_305293222_n-640x427.jpg","CGGtf1MuvLFB/KUrA/+mag==":"jumbotron.jpg","edceoMPEllS2CHPTCspg9g==":"dsc01293-1-1920x1080.jpg","Haq30jYBcfnT6FM/0Seksg==":"beauty%20care%205-1200x900.jpg","kxBnSopJjKCSEPAZ1jzaPg==":"beauty%20care%206-1200x900.jpg","dvOEeB2g0v26PTub0iuziw==":"dsc-1-2000x1342.jpg","IvF9AOgOj75uLkVmBiLsDQ==":"beauty%20care%207-1200x900.jpg","oC6k6hgA4Bii5A21eXIbEg==":"beauty%20care%208-1200x900.jpg","k+AhsPZDfeMk6X+T4b3/pA==":"beauty%20care%203-1200x900.jpg","O0hT4k3QlAi/DzHA5teMqA==":"beauty%20care%204-1200x900.jpg","/Sb3y9WTW+b4nZ/goppYAA==":"beauty%20care%209-1200x900.jpg","8CqgElmtGbCB9XzGCg/vJA==":"beauty%20care%2010-1200x900.jpg"}